multi_spi/fifo_gen.vhdl
-------------------------------------------------------------------------------
-- Title      : fifo generique
-- Project    : Source files in a directory tree, multiple compilers in same directory
-------------------------------------------------------------------------------
-- File       : fifo_gen.vhdl
-- Author     : yacine benaichouche  <TheGoldenAce@localhost.localdomain>
-- Company    : 
-- Created    : 2019-11-27
-- Last update: 2019-11-27
-- Platform   : 
-- Standard   : VHDL'93/02
-------------------------------------------------------------------------------
-- This is a multi-line project description
-- that can be used as a project dependent part of the file header.
-------------------------------------------------------------------------------
-- Description: 
-------------------------------------------------------------------------------
-- Copyright (c) 2019 
-------------------------------------------------------------------------------
-- Revisions  :
-- Date        Version  Author  Description
-- 2019-11-27  1.0      TheGoldenAce    Created
-------------------------------------------------------------------------------

library ieee;
use ieee.std_logic_1164.all;

-------------------------------------------------------------------------------

entity fifo_gen is

  generic (constant DATA_WIDTH_C : positive := 32;
           constant DATA_DEPTH_C : positive := 4
           );

  port (rst_n     : in  std_logic;
        clk       : in  std_logic;
        we_in     : in  std_logic;
        data_in   : in  std_logic_vector(DATA_WIDTH_C -1 downto 0);
        re_in     : in  std_logic;
        data_out  : out std_logic_vector(DATA_WIDTH_C -1 downto 0);
        full_out  : out std_logic;
        empty_out : out std_logic
        );

end entity fifo_gen;

-------------------------------------------------------------------------------

architecture rtl of fifo_gen is

  -----------------------------------------------------------------------------
  -- Internal signal declarations
  -----------------------------------------------------------------------------
  type r_memory is array (DATA_DEPTH_C -1 downto 0) of std_logic_vector(DATA_WIDTH_C -1 downto 0);
  signal FIFO_mem : r_memory;

  signal write_index : integer range 0 to DATA_DEPTH_C -1;
  signal read_index  : integer range 0 to DATA_DEPTH_C -1;

  signal r_data_out : std_logic_vector(DATA_WIDTH_C -1 downto 0);
  signal r_full     : std_logic;
  signal r_empty    : std_logic;
  signal r_diff_lap : std_logic;  -- to know if the read write index are on the
  -- same lap (empty or full => readindex =
  -- writeindex 


begin  -- architecture str

  -----------------------------------------------------------------------------
  -- Component instantiations
  -----------------------------------------------------------------------------
  control_process : process(rst_n, clk, we_in, re_in)
  begin
    if(rst_n = '0') then
      write_index <= 0;
      read_index  <= 0;
      r_empty     <= '1';
      r_full      <= '0';
      r_diff_lap  <= '0';
    else
      if (rising_edge(clk)) then
--------------------------------------------------------------------------------
---------------------------------- write cmd------------------------------------
--------------------------------------------------------------------------------
        if(we_in = '1') then
          if(write_index /= read_index or r_diff_lap = '0') then
            FIFO_mem(write_index) <= data_in;
            if (write_index = DATA_DEPTH_C -1) then
              write_index <= 0;
              r_diff_lap  <= '1';
            else
              write_index <= write_index + 1;
            end if;
          end if;
        end if;
--------------------------------------------------------------------------------
----------------------------------- read cmd------------------------------------
--------------------------------------------------------------------------------
        if(re_in = '1') then
          if(write_index /= read_index or r_diff_lap = '1') then
            r_data_out <= FIFO_mem(read_index);
            if(read_index = DATA_DEPTH_C -1) then
              read_index <= 0;
              r_diff_lap <= '0';
            else
              read_index <= read_index +1;
            end if;
          end if;
        end if;


--------------------------------------------------------------------------------
----------------------------------- full/empty----------------------------------
--------------------------------------------------------------------------------

        if (read_index = write_index) then
          if(r_diff_lap = '0') then
            r_empty <= '1';
          else
            r_full <= '1';
          end if;
        else
          r_empty <= '0';
          r_full  <= '0';
        end if;
      end if;
    end if;
  end process;



--------------------------------------------------------------------------------
----------------------------------- outputs ------------------------------------
--------------------------------------------------------------------------------
  data_out  <= r_data_out;
  full_out  <= r_full;
  empty_out <= r_empty;
end rtl;

multi_spi/tb_fifo_gen.vhdl
-------------------------------------------------------------------------------
-- Title      : tb_fifo_gen
-- Project    : Source files in a directory tree, multiple compilers in same directory
-------------------------------------------------------------------------------
-- File       : tb_fifo_gen.vhdl
-- Author     : yacine benaichouche  <TheGoldenAce@localhost.localdomain>
-- Company    : 
-- Created    : 2019-11-27
-- Last update: 2019-11-27
-- Platform   : 
-- Standard   : VHDL'93/02
-------------------------------------------------------------------------------
-- This is a multi-line project description
-- that can be used as a project dependent part of the file header.
-------------------------------------------------------------------------------
-- Description: tst bench for generique fifo 
-------------------------------------------------------------------------------
-- Copyright (c) 2019 
-------------------------------------------------------------------------------
-- Revisions  :
-- Date        Version  Author  Description
-- 2019-11-27  1.0      TheGoldenAce    Created
-------------------------------------------------------------------------------

library ieee;
use ieee.std_logic_1164.all;

-------------------------------------------------------------------------------

entity tb_fifo_gen is
end entity tb_fifo_gen;

-------------------------------------------------------------------------------

architecture tb of tb_fifo_gen is
  component fifo_gen
    generic (constant DATA_WIDTH_C :positive  ;
             constant DATA_DEPTH_C :positive 
             );

    port (rst_n     : in  std_logic;
          clk       : in  std_logic;
          we_in     : in  std_logic;
          data_in   : in  std_logic_vector (DATA_WIDTH_C -1 downto 0);
          re_in     : in  std_logic;
          data_out  : out std_logic_vector (DATA_WIDTH_C -1 downto 0);
          full_out  : out std_logic;
          empty_out : out std_logic);
  end component;


  -----------------------------------------------------------------------------
  -- Internal signal declarations
  -----------------------------------------------------------------------------

  constant DATA_WIDTH_C : positive := 32;
  constant DATA_DEPTH_C : positive := 4;

  signal rst_n     : std_logic;
  signal clk       : std_logic;
  signal we_in     : std_logic;
  signal data_in   : std_logic_vector (DATA_WIDTH_C -1 downto 0);
  signal re_in     : std_logic;
  signal data_out  : std_logic_vector (DATA_WIDTH_C -1 downto 0);
  signal full_out  : std_logic;
  signal empty_out : std_logic;

  constant TbPeriod : time      := 10 ns;
  signal TbClock    : std_logic := '0';



begin  -- architecture str

  -----------------------------------------------------------------------------
  -- Component instantiations
  -----------------------------------------------------------------------------

  dut : fifo_gen
    generic map (DATA_DEPTH_C => DATA_DEPTH_C,
                 DATA_WIDTH_C => DATA_WIDTH_C)
    port map (rst_n     => rst_n,
              clk       => clk,
              we_in     => we_in,
              data_in   => data_in,
              re_in     => re_in,
              data_out  => data_out,
              full_out  => full_out,
              empty_out => empty_out);

  -- Clock generation
  TbClock <= not TbClock after TbPeriod/2;

  -- EDIT: Check that clk is really your main clock signal
  clk <= TbClock;

  stimuli : process
  begin
    -- EDIT Adapt initialization as needed
    we_in   <= '0';
    data_in <= (others => '0');
    re_in   <= '0';
    -- Reset generation
    -- EDIT: Check that rst_n is really your reset signal
    rst_n   <= '0';
    wait for 10 * TbPeriod;
    rst_n   <= '1';
    wait for 10 * TbPeriod;
    data_in <= x"00000001";
    we_in   <= '1';
    wait for TbPeriod;
    we_in   <= '0';
    wait for TbPeriod;
    data_in <= x"ffffffff";
    we_in   <= '1';
    wait for TbPeriod;
    we_in   <= '0';
    wait for 2 * TbPeriod;
    re_in   <= '1';
    wait for TbPeriod;
    re_in   <= '0';
    wait for 2 * TbPeriod;
    re_in   <= '1';
    wait for TbPeriod;
    re_in   <= '0';
    wait for 2* TbPeriod;
    data_in <= x"00001111";
    we_in   <= '1';
    wait for TbPeriod;
    we_in   <= '0';
    wait for 2 * TbPeriod;
    re_in   <= '1';
    wait for TbPeriod;
    re_in   <= '0';

    wait;
  end process;

end tb;

-------------------------------------------------------------------------------

multi_spi/fifo_gen.vcd
$date
  Wed Nov 27 16:49:13 2019
$end
$version
  GHDL v0
$end
$timescale
  1 fs
$end
$scope module standard $end
$upscope $end
$scope module std_logic_1164 $end
$upscope $end
$scope module tb_fifo_gen $end
$var reg 1 ! rst_n $end
$var reg 1 " clk $end
$var reg 1 # we_in $end
$var reg 32 $ data_in[31:0] $end
$var reg 1 % re_in $end
$var reg 32 & data_out[31:0] $end
$var reg 1 ' full_out $end
$var reg 1 ( empty_out $end
$var reg 1 ) tbclock $end
$scope module dut $end
$var reg 1 * rst_n $end
$var reg 1 + clk $end
$var reg 1 , we_in $end
$var reg 32 - data_in[31:0] $end
$var reg 1 . re_in $end
$var reg 32 / data_out[31:0] $end
$var reg 1 0 full_out $end
$var reg 1 1 empty_out $end
$comment fifo_mem is not handled $end
$var integer 32 2 write_index $end
$var integer 32 3 read_index $end
$var reg 32 4 r_data_out[31:0] $end
$var reg 1 5 r_full $end
$var reg 1 6 r_empty $end
$var reg 1 7 r_diff_lap $end
$upscope $end
$upscope $end
$enddefinitions $end
#0
0!
0"
0#
b00000000000000000000000000000000 $
0%
bUUUUUUUUUUUUUUUUUUUUUUUUUUUUUUUU &
0'
1(
0)
0*
0+
0,
b00000000000000000000000000000000 -
0.
bUUUUUUUUUUUUUUUUUUUUUUUUUUUUUUUU /
00
11
b0 2
b0 3
bUUUUUUUUUUUUUUUUUUUUUUUUUUUUUUUU 4
05
16
07
#5000000
1"
1)
1+
#10000000
0"
0)
0+
#15000000
1"
1)
1+
#20000000
0"
0)
0+
#25000000
1"
1)
1+
#30000000
0"
0)
0+
#35000000
1"
1)
1+
#40000000
0"
0)
0+
#45000000
1"
1)
1+
#50000000
0"
0)
0+
#55000000
1"
1)
1+
#60000000
0"
0)
0+
#65000000
1"
1)
1+
#70000000
0"
0)
0+
#75000000
1"
1)
1+
#80000000
0"
0)
0+
#85000000
1"
1)
1+
#90000000
0"
0)
0+
#95000000
1"
1)
1+
#100000000
1!
0"
0)
1*
0+
#105000000
1"
1)
1+
#110000000
0"
0)
0+
#115000000
1"
1)
1+
#120000000
0"
0)
0+
#125000000
1"
1)
1+
#130000000
0"
0)
0+
#135000000
1"
1)
1+
#140000000
0"
0)
0+
#145000000
1"
1)
1+
#150000000
0"
0)
0+
#155000000
1"
1)
1+
#160000000
0"
0)
0+
#165000000
1"
1)
1+
#170000000
0"
0)
0+
#175000000
1"
1)
1+
#180000000
0"
0)
0+
#185000000
1"
1)
1+
#190000000
0"
0)
0+
#195000000
1"
1)
1+
#200000000
0"
1#
b00000000000000000000000000000001 $
0)
0+
1,
b00000000000000000000000000000001 -
#205000000
1"
1)
1+
b1 2
#210000000
0"
0#
0)
0+
0,
#215000000
1"
0(
1)
1+
01
06
#220000000
0"
1#
b11111111111111111111111111111111 $
0)
0+
1,
b11111111111111111111111111111111 -
#225000000
1"
1)
1+
b10 2
#230000000
0"
0#
0)
0+
0,
#235000000
1"
1)
1+
#240000000
0"
0)
0+
#245000000
1"
1)
1+
#250000000
0"
1%
0)
0+
1.
#255000000
1"
b00000000000000000000000000000001 &
1)
1+
b00000000000000000000000000000001 /
b1 3
b00000000000000000000000000000001 4
#260000000
0"
0%
0)
0+
0.
#265000000
1"
1)
1+
#270000000
0"
0)
0+
#275000000
1"
1)
1+
#280000000
0"
1%
0)
0+
1.
#285000000
1"
b11111111111111111111111111111111 &
1)
1+
b11111111111111111111111111111111 /
b10 3
b11111111111111111111111111111111 4
#290000000
0"
0%
0)
0+
0.
#295000000
1"
1(
1)
1+
11
16
#300000000
0"
0)
0+
#305000000
1"
1)
1+
#310000000
0"
1#
b00000000000000000001000100010001 $
0)
0+
1,
b00000000000000000001000100010001 -
#315000000
1"
1)
1+
b11 2
#320000000
0"
0#
0)
0+
0,
#325000000
1"
0(
1)
1+
01
06
#330000000
0"
0)
0+
#335000000
1"
1)
1+
#340000000
0"
1%
0)
0+
1.
#345000000
1"
b00000000000000000001000100010001 &
1)
1+
b00000000000000000001000100010001 /
b11 3
b00000000000000000001000100010001 4
#350000000
0"
0%
0)
0+
0.
#355000000
1"
1(
1)
1+
11
16
